ordinor/__init__.py
ordinor/constants.py
ordinor/exceptions.py
ordinor/analysis/__init__.py
ordinor/analysis/group_profiles/__init__.py
ordinor/analysis/group_profiles/distribution.py
ordinor/analysis/group_profiles/participation.py
ordinor/analysis/group_profiles/workload.py
ordinor/analysis/m2m/__init__.py
ordinor/analysis/m2m/cluster_intrinsic.py
ordinor/conformance/__init__.py
ordinor/conformance/_helpers.py
ordinor/conformance/fitness.py
ordinor/conformance/precision.py
ordinor/execution_context/__init__.py
ordinor/execution_context/base.py
ordinor/execution_context/direct_attribute.py
ordinor/execution_context/proxy.py
ordinor/execution_context/quality.py
ordinor/execution_context/rule_based/AtomicRule.py
ordinor/execution_context/rule_based/BaseSearch.py
ordinor/execution_context/rule_based/Rule.py
ordinor/execution_context/rule_based/TreeNode.py
ordinor/execution_context/rule_based/__init__.py
ordinor/execution_context/rule_based/decision_tree.py
ordinor/execution_context/rule_based/rule_generators.py
ordinor/execution_context/rule_based/score_funcs.py
ordinor/execution_context/rule_based/search.py
ordinor/io/__init__.py
ordinor/io/_helpers.py
ordinor/io/log_csv.py
ordinor/io/log_xes.py
ordinor/org_model_miner/__init__.py
ordinor/org_model_miner/_helpers.py
ordinor/org_model_miner/group_discovery.py
ordinor/org_model_miner/group_profiling.py
ordinor/org_model_miner/resource_features.py
ordinor/org_model_miner/clustering/__init__.py
ordinor/org_model_miner/clustering/agglomerative_hierarchical.py
ordinor/org_model_miner/clustering/fuzzy_cmeans.py
ordinor/org_model_miner/clustering/gaussian_mixture.py
ordinor/org_model_miner/clustering/moc.py
ordinor/org_model_miner/community/__init__.py
ordinor/org_model_miner/community/connected_comp.py
ordinor/org_model_miner/models/__init__.py
ordinor/org_model_miner/models/base.py
ordinor/social_network_miner/__init__.py
ordinor/social_network_miner/_helpers.py
ordinor/social_network_miner/causality.py
ordinor-0.2.1.dist-info/LICENSE
ordinor-0.2.1.dist-info/METADATA
ordinor-0.2.1.dist-info/WHEEL
ordinor-0.2.1.dist-info/top_level.txt
ordinor-0.2.1.dist-info/RECORD
