Metadata-Version: 2.1
Name: ordinor
Version: 0.2.1
Summary: Python toolkit for organizational model mining
Home-page: https://github.com/roy-jingyang/OrdinoR
Author: Jing (Roy) Yang
Author-email: roy.j.yang@qut.edu.au
Requires-Python: >=3.7
License-File: LICENSE
Requires-Dist: numpy>=1.17.2
Requires-Dist: scipy>=1.3.1
Requires-Dist: scikit-learn>=0.21.3
Requires-Dist: scikit-fuzzy>=0.4.1
Requires-Dist: pandas>=0.25.3
Requires-Dist: networkx>=2.4
Requires-Dist: pm4py>=1.2.4
Requires-Dist: Flask
Requires-Dist: flask-cors
Requires-Dist: flask-bootstrap
Requires-Dist: flask-wtf
Requires-Dist: flask-session
